{
	"info": {
		"_postman_id": "42817ae8-5335-43d8-ab9f-1e1e98c239b1",
		"name": "All Operations",
		"schema": "https://schema.getpostman.com/json/collection/v2.1.0/collection.json"
	},
	"item": [
		{
			"name": "Basic Verification",
			"event": [
				{
					"listen": "test",
					"script": {
						"exec": [
							"pm.test(\"Status code is 200\", function () {\r",
							"    pm.response.to.have.status(200);\r",
							"});\r",
							"pm.test(\"Body matches string\", function () {\r",
							"    pm.expect(pm.response.text(\"test data1\")).to.include(\"n0 delete it\");\r",
							"});\r",
							"pm.test(\"Response time is less than 600ms\", function () {\r",
							"    pm.expect(pm.response.responseTime).to.be.below(600);\r",
							"});"
						],
						"type": "text/javascript"
					}
				}
			],
			"request": {
				"method": "GET",
				"header": [],
				"url": {
					"raw": "http://localhost:3000/posts/4",
					"protocol": "http",
					"host": [
						"localhost"
					],
					"port": "3000",
					"path": [
						"posts",
						"4"
					]
				}
			},
			"response": []
		},
		{
			"name": "Delete",
			"request": {
				"method": "DELETE",
				"header": [],
				"url": {
					"raw": "http://localhost:3000/posts/3",
					"protocol": "http",
					"host": [
						"localhost"
					],
					"port": "3000",
					"path": [
						"posts",
						"3"
					]
				}
			},
			"response": []
		},
		{
			"name": "PUT",
			"request": {
				"method": "PUT",
				"header": [],
				"body": {
					"mode": "raw",
					"raw": "{\r\n  \"id\": 1,\r\n  \"title\": \"My new title\",\r\n  \"author\": \"updated author\"\r\n}",
					"options": {
						"raw": {
							"language": "json"
						}
					}
				},
				"url": {
					"raw": "http://localhost:3000/posts/1",
					"protocol": "http",
					"host": [
						"localhost"
					],
					"port": "3000",
					"path": [
						"posts",
						"1"
					]
				}
			},
			"response": []
		},
		{
			"name": "POST",
			"request": {
				"method": "POST",
				"header": [],
				"body": {
					"mode": "raw",
					"raw": "{\r\n    \"id\": 4,\r\n    \"title\": \"n0 delete it\",\r\n    \"author\": \"no delete\"\r\n  }",
					"options": {
						"raw": {
							"language": "json"
						}
					}
				},
				"url": {
					"raw": "http://localhost:3000/posts",
					"protocol": "http",
					"host": [
						"localhost"
					],
					"port": "3000",
					"path": [
						"posts"
					]
				}
			},
			"response": []
		},
		{
			"name": "GET",
			"request": {
				"method": "GET",
				"header": [],
				"url": {
					"raw": "http://localhost:3000/posts/2",
					"protocol": "http",
					"host": [
						"localhost"
					],
					"port": "3000",
					"path": [
						"posts",
						"2"
					]
				}
			},
			"response": []
		}
	]
}